rekker-0.1.14.dist-info/METADATA
rekker-0.1.14.dist-info/WHEEL
rekker-0.1.14.dist-info/license_files/LICENSE
rekker/__init__.py
rekker/rekker.cpython-38-x86_64-linux-gnu.so
rekker-0.1.14.dist-info/RECORD
