Metadata-Version: 2.3
Name: rekker
Version: 0.1.14
Classifier: Programming Language :: Rust
Classifier: Programming Language :: Python :: Implementation :: CPython
Classifier: Programming Language :: Python :: Implementation :: PyPy
License-File: LICENSE
Summary: Attack library written for rust and python
Keywords: tcp,attack
Author: GlacierSG <iamglaciersg@gmail.com>
Author-email: GlacierSG <iamglaciersg@gmail.com>
License: MIT
Requires-Python: >=3.7
Project-URL: Source Code, https://github.com/GlacierSG/rekker
